lista-3/subtractor/full-sub-1-bit/full_sub_1_bit.v
`timescale 1ns/1ns

module full_sub_1_bit (input wire X, Y, vemUm, output wire dif, vaiUm);
    
    assign dif = X ^ Y ^ vemUm;
    assign vaiUm = (~X&Y) | (Y & vemUm) | (~X & vemUm);

endmodule

lista-3/subtractor/full-sub-1-bit/full_sub_1_bit_tb.v
`timescale 1ns/5ns

`include "full_sub_1_bit.v"

module full_sub_1_bit_tb();
    reg x, y, cin;
    wire dif, cout;

    full_sub_1_bit uut(x, y ,cin, dif, cout);

    initial begin
        $dumpfile("full_sub_1_bit_tb.vcd");
        $dumpvars(0, full_sub_1_bit_tb);
        #50;
        x = 0; y = 0; cin = 0;
        #50;
        x = 0; y = 0; cin = 1;
        #50;
        x = 0; y = 1; cin = 0;
        #50;
        x = 0; y = 1; cin = 1;
        #50;
        x = 1; y = 0; cin = 0;
        #50;
        x = 1; y = 0; cin = 1;
        #50;
        x = 1; y = 1; cin = 0;
        #50;
        x = 1; y = 1; cin = 1;
        #50;

    end
endmodule

lista-3/subtractor/full-sub-1-bit/full_sub_1_bit_tb.vcd
$date
	Sun Apr  3 04:59:49 2022
$end
$version
	Icarus Verilog
$end
$timescale
	1ps
$end
$scope module full_sub_1_bit_tb $end
$var wire 1 ! dif $end
$var wire 1 " cout $end
$var reg 1 # cin $end
$var reg 1 $ x $end
$var reg 1 % y $end
$scope module uut $end
$var wire 1 $ X $end
$var wire 1 % Y $end
$var wire 1 ! dif $end
$var wire 1 " vaiUm $end
$var wire 1 # vemUm $end
$upscope $end
$upscope $end
$enddefinitions $end
#0
$dumpvars
x%
x$
x#
x"
x!
$end
#50000
0"
0!
0#
0%
0$
#100000
1"
1!
1#
#150000
0#
1%
#200000
0!
1#
#250000
0"
1!
0#
0%
1$
#300000
0!
1#
#350000
0#
1%
#400000
1"
1!
1#
