lista-2/encoder-1hot-8to3/encoder_1hot_8to3.v
module encoder_1hot_8to3_A (output wire [2:0] F,
input wire [7:0] A);

  assign F = (A == 8'b0000_0001) ? 3'b000 :
                       (A == 8'b0000_0010) ? 3'b001 :
                       (A == 8'b0000_0100) ? 3'b010 :
                       (A == 8'b0000_1000) ? 3'b011 :
                       (A == 8'b0001_0000) ? 3'b100 :
                       (A == 8'b0010_0000) ? 3'b101 :
                       (A == 8'b0100_0000) ? 3'b110 :
                       (A == 8'b1000_0000) ? 3'b111 : 3'bxxx;

endmodule

module encoder_1hot_8to3_B (output wire [2:0] F,
input wire [7:0] A);

    assign F[0] = A[1] || A[3] || A[5] || A[7];
    assign F[1] = A[2] || A[3] || A[6] || A[7];
    assign F[2] = A[4] || A[5] || A[6] || A[7];

endmodule

lista-2/encoder-1hot-8to3/encoder_1hot_8to3_tb.v
`timescale 1ms / 1ms
`include "encoder_1hot_8to3.v"

module encoder_1hot_8to3_tb;
    reg [7:0] A;
    wire [2:0] F;
    encoder_1hot_8to3_A uut(F, A);
    encoder_1hot_8to3_B dut(F, A);

    initial begin

        $dumpfile("encoder_1hot_8to3_tb.vcd");
        $dumpvars(0, encoder_1hot_8to3_tb);

        A = 8'b00000001;

        #50;
        
        A = 8'b00000010;

        #50;
        
        A = 8'b00000100;

        #50;
        
        A = 8'b00001000;

        #50;
        
        A = 8'b00010000;

        #50;
        
        A = 8'b00100000;

        #50;
        
        A = 8'b01000000;

        #50; 
        
        A = 8'b10000000;

        #50;
        $display("Complete");
    end
endmodule

lista-2/encoder-1hot-8to3/encoder_1hot_8to3_tb.vcd
$date
	Sun Mar  6 02:44:02 2022
$end
$version
	Icarus Verilog
$end
$timescale
	1ms
$end
$scope module encoder_1hot_8to3_tb $end
$var wire 3 ! F [2:0] $end
$var reg 8 " A [7:0] $end
$scope module dut $end
$var wire 8 # A [7:0] $end
$var wire 3 $ F [2:0] $end
$upscope $end
$scope module uut $end
$var wire 8 % A [7:0] $end
$var wire 3 & F [2:0] $end
$upscope $end
$upscope $end
$enddefinitions $end
#0
$dumpvars
b0 &
b1 %
b0 $
b1 #
b1 "
b0 !
$end
#50
b1 !
b1 $
b1 &
b10 "
b10 #
b10 %
#100
b10 !
b10 $
b10 &
b100 "
b100 #
b100 %
#150
b11 !
b11 $
b11 &
b1000 "
b1000 #
b1000 %
#200
b100 !
b100 $
b100 &
b10000 "
b10000 #
b10000 %
#250
b101 !
b101 $
b101 &
b100000 "
b100000 #
b100000 %
#300
b110 !
b110 $
b110 &
b1000000 "
b1000000 #
b1000000 %
#350
b111 !
b111 $
b111 &
b10000000 "
b10000000 #
b10000000 %
