mux-8to1/mux_8to1.v
module mux_8to1_A (output wire F,
    input wire [7:0] A, 
    input wire [2:0] Sel);

    assign F = (Sel == 3'b000) ? A[0] :
               (Sel == 3'b001) ? A[1] :
               (Sel == 3'b010) ? A[2] :
               (Sel == 3'b011) ? A[3] :
               (Sel == 3'b100) ? A[4] :
               (Sel == 3'b101) ? A[5] :
               (Sel == 3'b110) ? A[6] :
               (Sel == 3'b111) ? A[7] : 3'bXXX;

endmodule

module mux_8to1_B (output wire F,
    input wire [7:0] A,
    input wire [2:0] Sel);

    assign F = (A[0] & ~Sel[2] & ~Sel[1] & ~Sel[0]) |
               (A[1] & ~Sel[2] & ~Sel[1] &  Sel[0]) |
               (A[2] & ~Sel[2] &  Sel[1] & ~Sel[0]) |
               (A[3] & ~Sel[2] &  Sel[1] &  Sel[0]) |
               (A[4] &  Sel[2] & ~Sel[1] & ~Sel[0]) |
               (A[5] &  Sel[2] & ~Sel[1] &  Sel[0]) |
               (A[6] &  Sel[2] &  Sel[1] & ~Sel[0]) |
               (A[7] &  Sel[2] &  Sel[1] &  Sel[0]);
 
 
endmodule

lista-2/mux-8to1/mux_8to1_tb.v
`timescale 1ms / 1ms
`include "mux_8to1.v"

module mux_8to1_tb;
    wire F;
    reg [7:0] A;
    reg [2:0] Sel;

    mux_8to1_A uut(F, A, Sel);
    mux_8to1_A dut(F, A, Sel);

    initial begin

        $dumpfile("mux_8to1_tb.vcd");
        $dumpvars(0, mux_8to1_tb);

        Sel = 3'b000;    #50;
        A = 8'b00000001; #50;
        A = 8'b00000010; #50;
        A = 8'b00000100; #50;
        A = 8'b00001000; #50;
        A = 8'b00010000; #50;
        A = 8'b00100000; #50;
        A = 8'b01000000; #50;
        A = 8'b10000000; #50;
        A = 8'b00000000;

        Sel = 3'b001;    #50;
        A = 8'b00000001; #50;
        A = 8'b00000010; #50;
        A = 8'b00000100; #50;
        A = 8'b00001000; #50;
        A = 8'b00010000; #50;
        A = 8'b00100000; #50;
        A = 8'b01000000; #50;
        A = 8'b10000000; #50;
        A = 8'b00000000;

        Sel = 3'b010;    #50;
        A = 8'b00000001; #50;
        A = 8'b00000010; #50;
        A = 8'b00000100; #50;
        A = 8'b00001000; #50;
        A = 8'b00010000; #50;
        A = 8'b00100000; #50;
        A = 8'b01000000; #50;
        A = 8'b10000000; #50;
        A = 8'b00000000;

        Sel = 3'b011;    #50;
        A = 8'b00000001; #50;
        A = 8'b00000010; #50;
        A = 8'b00000100; #50;
        A = 8'b00001000; #50;
        A = 8'b00010000; #50;
        A = 8'b00100000; #50;
        A = 8'b01000000; #50;
        A = 8'b10000000; #50;
        A = 8'b00000000;

        Sel = 3'b100;    #50;
        A = 8'b00000001; #50;
        A = 8'b00000010; #50;
        A = 8'b00000100; #50;
        A = 8'b00001000; #50;
        A = 8'b00010000; #50;
        A = 8'b00100000; #50;
        A = 8'b01000000; #50;
        A = 8'b10000000; #50;
        A = 8'b00000000;


        Sel = 3'b101;    #50;
        A = 8'b00000001; #50;
        A = 8'b00000010; #50;
        A = 8'b00000100; #50;
        A = 8'b00001000; #50;
        A = 8'b00010000; #50;
        A = 8'b00100000; #50;
        A = 8'b01000000; #50;
        A = 8'b10000000; #50;
        A = 8'b00000000;

        Sel = 3'b110; #50;
        A = 8'b00000001; #50;
        A = 8'b00000010; #50;
        A = 8'b00000100; #50;
        A = 8'b00001000; #50;
        A = 8'b00010000; #50;
        A = 8'b00100000; #50;
        A = 8'b01000000; #50;
        A = 8'b10000000; #50;
        A = 8'b00000000;


        Sel = 3'b111;    #50;
        A = 8'b00000001; #50;
        A = 8'b00000010; #50;
        A = 8'b00000100; #50;
        A = 8'b00001000; #50;
        A = 8'b00010000; #50;
        A = 8'b00100000; #50;
        A = 8'b01000000; #50;
        A = 8'b10000000; #50;
        A = 8'b00000000;
    end
endmodule

lista-2/mux-8to1/mux_8to1_tb.vcd
$date
	Tue Mar  8 02:51:31 2022
$end
$version
	Icarus Verilog
$end
$timescale
	1ms
$end
$scope module mux_8to1_tb $end
$var wire 1 ! F $end
$var reg 8 " A [7:0] $end
$var reg 3 # Sel [2:0] $end
$scope module dut $end
$var wire 8 $ A [7:0] $end
$var wire 1 ! F $end
$var wire 3 % Sel [2:0] $end
$upscope $end
$scope module uut $end
$var wire 8 & A [7:0] $end
$var wire 1 ! F $end
$var wire 3 ' Sel [2:0] $end
$upscope $end
$upscope $end
$enddefinitions $end
#0
$dumpvars
b0 '
bx &
b0 %
bx $
b0 #
bx "
x!
$end
#50
1!
b1 "
b1 $
b1 &
#100
0!
b10 "
b10 $
b10 &
#150
b100 "
b100 $
b100 &
#200
b1000 "
b1000 $
b1000 &
#250
b10000 "
b10000 $
b10000 &
#300
b100000 "
b100000 $
b100000 &
#350
b1000000 "
b1000000 $
b1000000 &
#400
b10000000 "
b10000000 $
b10000000 &
#450
b1 #
b1 %
b1 '
b0 "
b0 $
b0 &
#500
b1 "
b1 $
b1 &
#550
1!
b10 "
b10 $
b10 &
#600
0!
b100 "
b100 $
b100 &
#650
b1000 "
b1000 $
b1000 &
#700
b10000 "
b10000 $
b10000 &
#750
b100000 "
b100000 $
b100000 &
#800
b1000000 "
b1000000 $
b1000000 &
#850
b10000000 "
b10000000 $
b10000000 &
#900
b10 #
b10 %
b10 '
b0 "
b0 $
b0 &
#950
b1 "
b1 $
b1 &
#1000
b10 "
b10 $
b10 &
#1050
1!
b100 "
b100 $
b100 &
#1100
0!
b1000 "
b1000 $
b1000 &
#1150
b10000 "
b10000 $
b10000 &
#1200
b100000 "
b100000 $
b100000 &
#1250
b1000000 "
b1000000 $
b1000000 &
#1300
b10000000 "
b10000000 $
b10000000 &
#1350
b11 #
b11 %
b11 '
b0 "
b0 $
b0 &
#1400
b1 "
b1 $
b1 &
#1450
b10 "
b10 $
b10 &
#1500
b100 "
b100 $
b100 &
#1550
1!
b1000 "
b1000 $
b1000 &
#1600
0!
b10000 "
b10000 $
b10000 &
#1650
b100000 "
b100000 $
b100000 &
#1700
b1000000 "
b1000000 $
b1000000 &
#1750
b10000000 "
b10000000 $
b10000000 &
#1800
b100 #
b100 %
b100 '
b0 "
b0 $
b0 &
#1850
b1 "
b1 $
b1 &
#1900
b10 "
b10 $
b10 &
#1950
b100 "
b100 $
b100 &
#2000
b1000 "
b1000 $
b1000 &
#2050
1!
b10000 "
b10000 $
b10000 &
#2100
0!
b100000 "
b100000 $
b100000 &
#2150
b1000000 "
b1000000 $
b1000000 &
#2200
b10000000 "
b10000000 $
b10000000 &
#2250
b101 #
b101 %
b101 '
b0 "
b0 $
b0 &
#2300
b1 "
b1 $
b1 &
#2350
b10 "
b10 $
b10 &
#2400
b100 "
b100 $
b100 &
#2450
b1000 "
b1000 $
b1000 &
#2500
b10000 "
b10000 $
b10000 &
#2550
1!
b100000 "
b100000 $
b100000 &
#2600
0!
b1000000 "
b1000000 $
b1000000 &
#2650
b10000000 "
b10000000 $
b10000000 &
#2700
b110 #
b110 %
b110 '
b0 "
b0 $
b0 &
#2750
b1 "
b1 $
b1 &
#2800
b10 "
b10 $
b10 &
#2850
b100 "
b100 $
b100 &
#2900
b1000 "
b1000 $
b1000 &
#2950
b10000 "
b10000 $
b10000 &
#3000
b100000 "
b100000 $
b100000 &
#3050
1!
b1000000 "
b1000000 $
b1000000 &
#3100
0!
b10000000 "
b10000000 $
b10000000 &
#3150
b111 #
b111 %
b111 '
b0 "
b0 $
b0 &
#3200
b1 "
b1 $
b1 &
#3250
b10 "
b10 $
b10 &
#3300
b100 "
b100 $
b100 &
#3350
b1000 "
b1000 $
b1000 &
#3400
b10000 "
b10000 $
b10000 &
#3450
b100000 "
b100000 $
b100000 &
#3500
b1000000 "
b1000000 $
b1000000 &
#3550
1!
b10000000 "
b10000000 $
b10000000 &
#3600
0!
b0 "
b0 $
b0 &
